pnprint/__init__.py
pnprint/_test.py
pnprint-1.3.dist-info/METADATA
pnprint-1.3.dist-info/WHEEL
pnprint-1.3.dist-info/RECORD
