Metadata-Version: 2.3
Name: pnprint
Version: 1.3
Summary: format and color serialized data strings to make them more human readable
License: GNU LGPL v3
Author: jimy-byerley
Author-email: jimy.byerley@gmail.com
Requires-Python: >=3.8,<4.0
Classifier: License :: Other/Proprietary License
Classifier: Programming Language :: Python :: 3
Classifier: Programming Language :: Python :: 3.8
Classifier: Programming Language :: Python :: 3.9
Classifier: Programming Language :: Python :: 3.10
Classifier: Programming Language :: Python :: 3.11
Classifier: Programming Language :: Python :: 3.12
Classifier: Programming Language :: Python :: 3.13
